Metadata-Version: 2.1
Name: ckmeans-1d-dp
Version: 4.3.4.4
Summary: A python interface for the Ckmeans.1d.dp R package
Author: Alden Bradford
License:                    GNU LESSER GENERAL PUBLIC LICENSE
Project-URL: homepage, https://github.com/AldenMB/Ckmeans.1d.dp
Classifier: Programming Language :: Python :: 3
Classifier: Operating System :: OS Independent
Requires-Python: >=3.7
License-File: LICENSE
